Arduino/__init__.py
Arduino/arduino.py
Arduino/test_arduino.py
Arduino/test_main.py
arduino_python3-0.6.dist-info/METADATA
arduino_python3-0.6.dist-info/WHEEL
arduino_python3-0.6.dist-info/top_level.txt
arduino_python3-0.6.dist-info/RECORD
