Metadata-Version: 2.1
Name: arduino-python3
Version: 0.6
Summary: A light-weight Python library that provides a serial   bridge for communicating with Arduino microcontroller boards. Extended to work with Python 3
Home-page: https://github.com/mkals/Arduino-Python3-Command-API
Author: Morten Kals
Author-email: morten@kals.no
License: MIT
Platform: UNKNOWN
